pyarinst/__init__.py
pyarinst/pyarinst.py
pyarinst-1.0.1.dist-info/LICENSE
pyarinst-1.0.1.dist-info/METADATA
pyarinst-1.0.1.dist-info/WHEEL
pyarinst-1.0.1.dist-info/top_level.txt
pyarinst-1.0.1.dist-info/RECORD
