Metadata-Version: 2.1
Name: pyarinst
Version: 1.0.1
Summary: Python SDK for Arinst devices
Author: Ilya Danilenko
License-File: LICENSE
Requires-Dist: pyserial
